terminable-0.1.2.dist-info/METADATA
terminable-0.1.2.dist-info/WHEEL
terminable-0.1.2.dist-info/license_files/LICENSE
terminable/__init__.pyi
terminable/__init__.py
terminable/types.py
terminable/py.typed
terminable/terminable.cpython-310-darwin.so
terminable-0.1.2.dist-info/RECORD
