Metadata-Version: 2.1
Name: terminable
Version: 0.1.2
Classifier: Programming Language :: Rust
Classifier: Programming Language :: Python :: Implementation :: CPython
Classifier: Programming Language :: Python :: Implementation :: PyPy
License-File: LICENSE
Requires-Python: >=3.7
Project-URL: Homepage, https://github.com/abrauninger/terminable
Project-URL: Bug Tracker, https://github.com/abrauninger/terminable/issues
